odoo/addons/website_require_login/README.rst
odoo/addons/website_require_login/__init__.py
odoo/addons/website_require_login/__manifest__.py
odoo/addons/website_require_login/data/ir_actions.xml
odoo/addons/website_require_login/data/ir_ui_menu.xml
odoo/addons/website_require_login/i18n/es.po
odoo/addons/website_require_login/i18n/it.po
odoo/addons/website_require_login/i18n/website_require_login.pot
odoo/addons/website_require_login/models/__init__.py
odoo/addons/website_require_login/models/ir_http.py
odoo/addons/website_require_login/models/website_auth_url.py
odoo/addons/website_require_login/readme/CONTRIBUTORS.md
odoo/addons/website_require_login/readme/DESCRIPTION.md
odoo/addons/website_require_login/readme/USAGE.md
odoo/addons/website_require_login/security/ir.model.access.csv
odoo/addons/website_require_login/static/description/icon.png
odoo/addons/website_require_login/static/description/index.html
odoo/addons/website_require_login/tests/__init__.py
odoo/addons/website_require_login/tests/test_ir_http.py
odoo/addons/website_require_login/views/website_auth_url.xml
odoo_addon_website_require_login-18.0.1.0.0.2.dist-info/METADATA
odoo_addon_website_require_login-18.0.1.0.0.2.dist-info/WHEEL
odoo_addon_website_require_login-18.0.1.0.0.2.dist-info/top_level.txt
odoo_addon_website_require_login-18.0.1.0.0.2.dist-info/RECORD
